ajperry_pipeline/__init__.py
ajperry_pipeline/base.py
ajperry_pipeline/main.py
ajperry_pipeline/ml/__init__.py
ajperry_pipeline/ml/data/__init__.py
ajperry_pipeline/ml/data/imagenet.py
ajperry_pipeline/ml/data/reddit.py
ajperry_pipeline/ml/models/__init__.py
ajperry_pipeline/ml/models/blocks/__init__.py
ajperry_pipeline/ml/models/blocks/decoder.py
ajperry_pipeline/ml/models/blocks/embedding.py
ajperry_pipeline/ml/models/blocks/encoder.py
ajperry_pipeline/ml/models/blocks/feed_forward_neural_network.py
ajperry_pipeline/ml/models/blocks/layer_normalization.py
ajperry_pipeline/ml/models/blocks/projection.py
ajperry_pipeline/ml/models/blocks/self_attention.py
ajperry_pipeline/ml/models/image_classifier.py
ajperry_pipeline/ml/models/transformer.py
ajperry_pipeline/ml/utils/__init__.py
ajperry_pipeline/ml/utils/reddit.py
ajperry_pipeline/utils.py
ajperry_pipeline-0.1.23.dist-info/METADATA
ajperry_pipeline-0.1.23.dist-info/WHEEL
ajperry_pipeline-0.1.23.dist-info/entry_points.txt
ajperry_pipeline-0.1.23.dist-info/RECORD
