Metadata-Version: 2.3
Name: ajperry-pipeline
Version: 0.1.23
Summary: 
Author: Alan Perry
Author-email: alan.jacob.perry@gmail.com
Requires-Python: >=3.10
Classifier: Programming Language :: Python :: 3
Classifier: Programming Language :: Python :: 3.10
Classifier: Programming Language :: Python :: 3.11
Classifier: Programming Language :: Python :: 3.12
Classifier: Programming Language :: Python :: 3.13
Provides-Extra: lint
Provides-Extra: test
Requires-Dist: einops
Requires-Dist: kfp (>=2.0.0,<3)
Requires-Dist: pandas
Requires-Dist: pytest ; extra == "test"
Requires-Dist: ruff ; extra == "lint"
Requires-Dist: torch
Requires-Dist: torchtext
Requires-Dist: torchvision
Requires-Dist: transformers
Requires-Dist: typer
